Crosscap-0.5.0.data/scripts/urltool
crosscap/__init__.py
crosscap/_version.py
crosscap/doc.py
crosscap/interface.py
crosscap/openapi.py
crosscap/testing.py
crosscap/tree.py
crosscap/urltool.py
crosscap/yamlhack.py
crosscap/permitting/__init__.py
crosscap/permitting/core.py
crosscap/test/__init__.py
crosscap/test/conftest.py
crosscap/test/test_doc.py
crosscap/test/test_openapi.py
crosscap/test/test_permitting.py
crosscap/test/test_testing.py
crosscap/test/test_tree.py
crosscap/test/test_urltool.py
crosscap/test/test_version.py
Crosscap-0.5.0.dist-info/LICENSE
Crosscap-0.5.0.dist-info/METADATA
Crosscap-0.5.0.dist-info/WHEEL
Crosscap-0.5.0.dist-info/top_level.txt
Crosscap-0.5.0.dist-info/RECORD
