Metadata-Version: 2.1
Name: Crosscap
Version: 0.5.0
Summary: Suite of tools for enhancing the Klein web framework
Home-page: https://github.com/corydodt/Crosscap
Author: Cory Dodt
Author-email: corydodt@gmail.com
License: UNKNOWN
Platform: UNKNOWN
Classifier: Programming Language :: Python :: 2
Classifier: Programming Language :: Python :: 3
Classifier: License :: OSI Approved :: MIT License
Requires-Dist: click (>=6.7)
Requires-Dist: future (>=0.16.0)
Requires-Dist: klein
Requires-Dist: pyjwt (>=1.7.1)
Requires-Dist: pyyaml (>=3.12)
Requires-Dist: twisted (>=17.1.0)
Requires-Dist: werkzeug (>=0.13)
Requires-Dist: wrapt (>=1.11.1)
Requires-Dist: ftfy (==4.4.3) ; python_version < "3"
Requires-Dist: ftfy ; python_version >= "3"
Provides-Extra: dev
Requires-Dist: pytest-cov ; extra == 'dev'
Requires-Dist: pytest-twisted ; extra == 'dev'
Requires-Dist: pytest ; extra == 'dev'
Requires-Dist: mock ; extra == 'dev'
Requires-Dist: pyflakes ; extra == 'dev'
Requires-Dist: pytest-flakes ; extra == 'dev'
Requires-Dist: pytz ; extra == 'dev'
Requires-Dist: tox ; extra == 'dev'
